
[
  {"id":"a_001", "title":"Vipizrer", "content":"LWITFA KanRc", "color":"#69FF15"},
  {"id":"a_002", "title":"Naloig", "content":"cNnlk AQmgu", "color":"#CF8F47"},
  {"id":"a_003", "title":"Vetusfid", "content":"MoGYYIM vLcSG", "color":"#9DC4E4"},
  {"id":"a_004", "title":"Potopus", "content":"CuzAUAae xkrvV", "color":"#A40985"},
  {"id":"a_005", "title":"Nidjuzvaw", "content":"MufRSsZL IZZfB", "color":"#30F901"},
  {"id":"a_006", "title":"Amazila", "content":"RigrLdM vrkzD", "color":"#A6A48C"},
  {"id":"a_007", "title":"Vuvekud", "content":"ZGpmQA dFCGwz", "color":"#C0592A"},
  {"id":"a_008", "title":"Hubewez", "content":"PanJhcOL usmnA", "color":"#24533C"},
  {"id":"a_009", "title":"Igoiwoom", "content":"CurFqnd TfIar", "color":"#7CEDAC"},
  {"id":"a_010", "title":"Gidotog", "content":"BbObbX jQSJO", "color":"#FA285B"}
]
